{"income": {"fiscal_year": ["2011", "2012", "2013", "2014", "2015", "2016", "2017", "2018", "2019", "2020"], "quarter_count": [4, 4, 4, 4, 4, 4, 4, 4, 4, 4], "latest_quarter": ["Q4", "Q4", "Q4", "Q4", "Q4", "Q4", "Q4", "Q4", "Q4", "Q4"], "revenue": [2252, 2466, 2504, 2795, 2539, 2309, 2464, 2565, 2266, 2050], "cost_of_revenue": [-2112, -2289, -2319, -2576, -2320, -2095, -2237, -2343, -2081, -1876], "gross_profit": [136, 174, 184, 218, 216, 211, 226, 219, 183, 173], "operating_expenses": [-87, -88, -98, -114, -110, -124, -138, -151, -134, -129], "selling_general_and_admin": [-87, -88, -98, -114, -110, -112, -129, -141, -125, -120], "depreciation_and_amortization": [0, 0, 0, 0, 0, -5, -8, -8, -8, -7], "operating_income": [46, 86, 85, 103, 105, 87, 85, 66, 47, 42], "non_operating_income": [0, 0, 0, -1, -2, -6, -4, -2, -1, -6], "interest_expense_net": [0, 0, 0, 0, -1, -5, -2, -2, 0, -6], "pretax_income_adj": [47, 85, 85, 101, 102, 79, 80, 63, 47, 33], "abnormal_gains": [0, -11, 29, -3, -12, -10, -7, -7, -18, -16], "pretax_income": [41, 73, 115, 97, 88, 65, 71, 53, 27, 17], "income_tax_net": [11, -17, -4, -16, 6, -3, -103, -33, -3, -2], "income_fr_continuing_ops": [49, 55, 109, 80, 94, 62, -33, 21, 23, 12], "net_income": [49, 55, 109, 80, 94, 62, -33, 21, 23, 12]}, "balance": {"fiscal_year": ["2011", "2012", "2013", "2014", "2015", "2016", "2017", "2018", "2019", "2020"], "latest_quarter": ["Q4", "Q4", "Q4", "Q4", "Q4", "Q4", "Q4", "Q4", "Q4", "Q4"], "shares_basic": [57, 55, 53, 53, 50, 49, 49, 43, 36, 36], "shares_diluted": [58, 55, 54, 53, 51, 49, 48, 44, 37, 36], "cash_and_st_inv": [283, 384, 345, 427, 465, 681, 742, 458, 347, 390], "receivables": [425, 459, 559, 520, 479, 440, 436, 468, 324, 309], "inventories": [391, 324, 396, 401, 411, 381, 268, 309, 314, 327], "current_assets": [1201, 1214, 1342, 1378, 1388, 1531, 1630, 1403, 1195, 1202], "ppe_net": [163, 176, 185, 190, 178, 166, 186, 210, 205, 185], "lt_inv_and_receivables": [24, 10, 9, 0, 0, 0, 0, 0, 0, 0], "other_lt_assets": [110, 100, 119, 106, 327, 300, 292, 285, 358, 356], "non_current_assets": [298, 287, 314, 296, 505, 467, 478, 496, 564, 541], "assets": [1499, 1501, 1657, 1675, 1893, 1998, 2109, 1899, 1759, 1744], "payables": [290, 264, 330, 295, 256, 329, 374, 432, 310, 387], "st_debt": [0, 0, 0, 0, 12, 12, 18, 6, 8, 9], "current_liabilities": [351, 330, 398, 359, 333, 412, 478, 537, 459, 481], "lt_debt": [10, 10, 9, 8, 222, 211, 193, 147, 138, 131], "non_current_liabilities": [32, 31, 31, 26, 238, 220, 291, 230, 285, 273], "liabilities": [384, 361, 430, 385, 571, 633, 770, 767, 745, 754], "share_capital": [680, 656, 649, 655, 630, 631, 639, 559, 515, 514], "retained_earnings": [449, 493, 586, 644, 704, 748, 708, 584, 515, 492], "equity": [1115, 1139, 1227, 1289, 1321, 1365, 1339, 1132, 1014, 989], "liabilities_and_equity": [1499, 1501, 1657, 1675, 1893, 1998, 2109, 1899, 1759, 1744]}, "cashflow": {"fiscal_year": ["2011", "2012", "2013", "2014", "2015", "2016", "2017", "2018", "2019", "2020"], "quarter_count": [4, 4, 4, 4, 4, 4, 4, 4, 4, 4], "latest_quarter": ["Q4", "Q4", "Q4", "Q4", "Q4", "Q4", "Q4", "Q4", "Q4", "Q4"], "net_income": [49, 55, 109, 80, 94, 62, -33, 21, 23, 12], "depreciation_and_amortization": [33, 34, 39, 44, 49, 53, 48, 50, 47, 47], "non_cash_items": [-23, 14, -6, 15, -5, 10, 15, 19, 10, 11], "change_in_working_capital": [-10, 43, -46, -8, 7, 140, 113, -16, 10, 46], "cash_fr_operating": [55, 150, 97, 133, 147, 271, 144, 76, 92, 119], "change_in_ppe_and_intangibles": [-69, -46, -23, -42, -34, -28, -48, -61, -30, -32], "change_in_lt_investment": [9, 15, 0, 9, 0, 0, 0, 0, 0, 0], "net_cash_fr_acq_disp": [0, 0, -75, 5, -229, 0, 0, -2, 0, 3], "cash_fr_investing": [-59, -8, -107, -26, -265, -20, -54, -66, -34, -32], "dividends_paid": [0, 0, 0, 0, 0, 0, 0, -13, -21, -20], "cash_fr_debt_issued": [0, 0, 0, 0, 229, -12, -12, -56, -5, -7], "cash_fr_equity_issued": [-52, -40, -27, -24, -64, -22, -19, -207, -118, -23], "cash_fr_financing": [-52, -41, -27, -24, 161, -34, -31, -289, -151, -57], "net_change_in_cash": [-61, 99, -39, 80, 37, 214, 61, -282, -94, 32]}}