{"income": {"fiscal_year": ["2020"], "quarter_count": [4], "latest_quarter": ["Q4"], "revenue": [1252], "cost_of_revenue": [-437], "gross_profit": [813], "operating_expenses": [-794], "selling_general_and_admin": [-543], "depreciation_and_amortization": [-301], "operating_income": [20], "non_operating_income": [-110], "interest_expense_net": [-110], "pretax_income_adj": [-91], "abnormal_gains": [-259], "pretax_income": [-351], "income_tax_net": [3], "income_fr_continuing_ops": [-348], "net_income": [-348]}, "balance": {"fiscal_year": ["2020"], "latest_quarter": ["Q4"], "shares_basic": [601], "shares_diluted": [601], "cash_and_st_inv": [257], "receivables": [737], "current_assets": [1147], "ppe_net": [36], "other_lt_assets": [13606], "non_current_assets": [13643], "assets": [14790], "payables": [651], "st_debt": [28], "current_liabilities": [1423], "lt_debt": [3457], "non_current_liabilities": [4332], "liabilities": [5755], "share_capital": [9989], "treasury_stock": [-196], "retained_earnings": [-1250], "equity": [9034], "liabilities_and_equity": [14790]}, "cashflow": {"fiscal_year": ["2020"], "quarter_count": [4], "latest_quarter": ["Q4"], "net_income": [-348], "depreciation_and_amortization": [301], "non_cash_items": [194], "change_in_working_capital": [115], "cash_fr_operating": [262], "change_in_ppe_and_intangibles": [-71], "net_cash_fr_acq_disp": [-2916], "cash_fr_investing": [-2986], "cash_fr_debt_issued": [1881], "cash_fr_equity_issued": [1122], "cash_fr_financing": [2925], "net_change_in_cash": [196]}}