{"income": {"fiscal_year": ["2014", "2015", "2016", "2017", "2018", "2019", "2020"], "quarter_count": [4, 4, 4, 4, 4, 4, 4], "latest_quarter": ["Q4", "Q4", "Q4", "Q4", "Q4", "Q4", "Q4"], "revenue": [3309, 4710, 4491, 4717, 5236, 5551, 4060], "cost_of_revenue": [-1292, -1913, -1831, -1857, -2055, -2280, -1463], "gross_profit": [2014, 2796, 2659, 2857, 3178, 3271, 2597], "operating_expenses": [-1005, -1609, -1760, -1956, -2298, -2713, -2230], "selling_general_and_admin": [-925, -1426, -1539, -1747, -2074, -2464, -2018], "depreciation_and_amortization": [-78, -181, -218, -207, -222, -249, -212], "operating_income": [1008, 1184, 898, 900, 878, 558, 367], "non_operating_income": [0, -2, -1, -7, -112, -23, -16], "interest_expense_net": [0, -1, -3, -21, -35, -18, -43], "pretax_income_adj": [1008, 1183, 897, 892, 764, 535, 351], "abnormal_gains": [0, 0, -4, -69, -143, -750, -348], "pretax_income": [1007, 1172, 687, 741, 620, -215, 3], "income_tax_net": [-345, -333, -136, -147, -77, -10, -66], "income_fr_continuing_ops": [659, 835, 551, 590, 541, -225, -63], "net_income": [659, 836, 552, 590, 541, -221, -61]}, "balance": {"fiscal_year": ["2014", "2015", "2016", "2017", "2018", "2019", "2020"], "latest_quarter": ["Q4", "Q4", "Q4", "Q4", "Q4", "Q4", "Q4"], "shares_basic": [203, 199, 177, 159, 150, 149, 150], "shares_diluted": [206, 203, 179, 161, 152, 145, 151], "cash_and_st_inv": [971, 978, 227, 163, 172, 592, 232], "receivables": [298, 363, 265, 290, 383, 308, 373], "inventories": [426, 519, 549, 660, 953, 827, 736], "current_assets": [1777, 1989, 1164, 1262, 1729, 1894, 1546], "ppe_net": [350, 562, 591, 583, 615, 561, 485], "other_lt_assets": [89, 132, 653, 2213, 4306, 5491, 5450], "non_current_assets": [439, 694, 1244, 2796, 4921, 6052, 5935], "assets": [2216, 2684, 2409, 4059, 6650, 7946, 7481], "payables": [308, 326, 432, 760, 912, 804, 1051], "st_debt": [0, 0, 133, 200, 630, 167, 123], "current_liabilities": [308, 326, 565, 960, 1542, 1401, 1621], "lt_debt": [0, 0, 0, 674, 1936, 2012, 1219], "non_current_liabilities": [102, 117, 248, 1077, 2672, 4377, 3703], "liabilities": [410, 443, 814, 2037, 4214, 5778, 5324], "share_capital": [527, 636, 767, 831, 1011, 1085, 1158], "treasury_stock": [-2, -497, -2654, -3015, -3223, -3325, -3326], "retained_earnings": [1287, 2168, 3560, 4152, 4707, 4332, 4270], "equity": [1806, 2241, 1595, 2021, 2436, 2168, 2157], "liabilities_and_equity": [2216, 2684, 2409, 4059, 6650, 7946, 7481]}, "cashflow": {"fiscal_year": ["2014", "2015", "2016", "2017", "2018", "2019", "2020"], "quarter_count": [4, 4, 4, 4, 4, 4, 4], "latest_quarter": ["Q4", "Q4", "Q4", "Q4", "Q4", "Q4", "Q4"], "net_income": [659, 835, 551, 590, 541, -225, -63], "depreciation_and_amortization": [78, 181, 218, 207, 222, 249, 212], "non_cash_items": [-40, 48, 181, 103, 92, 703, 197], "change_in_working_capital": [-68, 181, 80, 157, -163, 132, 278], "cash_fr_operating": [632, 1249, 1032, 1061, 694, 859, 624], "change_in_ppe_and_intangibles": [-212, -378, -169, -122, -181, -223, -111], "net_cash_fr_acq_disp": [0, 0, -480, -1414, -1874, -13, -13], "cash_fr_investing": [-214, -379, -649, -1531, -2123, 62, -124], "cash_fr_debt_issued": [0, -7, 146, 737, 1646, -394, -868], "cash_fr_equity_issued": [16, -1140, -995, -347, -177, -102, 2], "cash_fr_financing": [69, -1150, -848, 391, 1452, -497, -870], "net_change_in_cash": [483, -276, -471, -66, 9, 420, -358]}, "income_yoy": {"fiscal_year": ["2014", "2015", "2016", "2017", "2018", "2019", "2020"], "revenue": [null, 0.423, -0.046, 0.05, 0.11, 0.06, -0.269], "cost_of_revenue": [null, 0.481, -0.043, 0.014, 0.107, 0.109, -0.358], "gross_profit": [null, 0.388, -0.049, 0.074, 0.112, 0.029, -0.206], "operating_expenses": [null, 0.601, 0.094, 0.111, 0.175, 0.181, -0.178], "selling_general_and_admin": [null, 0.542, 0.079, 0.135, 0.187, 0.188, -0.181], "depreciation_and_amortization": [null, 1.321, 0.204, -0.05, 0.072, 0.122, -0.149], "operating_income": [null, 0.175, -0.242, 0.002, -0.024, -0.364, -0.342], "non_operating_income": [null, null, -0.5, 6.0, 15.0, -0.795, -0.304], "interest_expense_net": [null, null, 2.0, 6.0, 0.667, -0.486, 1.389], "pretax_income_adj": [null, 0.174, -0.242, -0.006, -0.143, -0.3, -0.344], "abnormal_gains": [null, null, null, 16.25, 1.072, 4.245, -0.536], "pretax_income": [null, 0.164, -0.414, 0.079, -0.163, -1.347, -1.014], "income_tax_net": [null, -0.035, -0.592, 0.081, -0.476, -0.87, 5.6], "income_fr_continuing_ops": [null, 0.267, -0.34, 0.071, -0.083, -1.416, -0.72], "net_income": [null, 0.269, -0.34, 0.069, -0.083, -1.409, -0.724]}, "balance_yoy": {"fiscal_year": ["2014", "2015", "2016", "2017", "2018", "2019", "2020"], "cash_and_st_inv": [null, 0.007, -0.768, -0.282, 0.055, 2.442, -0.608], "receivables": [null, 0.218, -0.27, 0.094, 0.321, -0.196, 0.211], "inventories": [null, 0.218, 0.058, 0.202, 0.444, -0.132, -0.11], "current_assets": [null, 0.119, -0.415, 0.084, 0.37, 0.095, -0.184], "ppe_net": [null, 0.606, 0.052, -0.014, 0.055, -0.088, -0.135], "other_lt_assets": [null, 0.483, 3.947, 2.389, 0.946, 0.275, -0.007], "non_current_assets": [null, 0.581, 0.793, 1.248, 0.76, 0.23, -0.019], "assets": [null, 0.211, -0.102, 0.685, 0.638, 0.195, -0.059], "payables": [null, 0.058, 0.325, 0.759, 0.2, -0.118, 0.307], "st_debt": [null, null, null, 0.504, 2.15, -0.735, -0.263], "current_liabilities": [null, 0.058, 0.733, 0.699, 0.606, -0.091, 0.157], "lt_debt": [null, null, null, null, 1.872, 0.039, -0.394], "non_current_liabilities": [null, 0.147, 1.12, 3.343, 1.481, 0.638, -0.154], "liabilities": [null, 0.08, 0.837, 1.502, 1.069, 0.371, -0.079], "share_capital": [null, 0.207, 0.206, 0.083, 0.217, 0.073, 0.067], "treasury_stock": [null, 247.5, 4.34, 0.136, 0.069, 0.032, 0.0], "retained_earnings": [null, 0.685, 0.642, 0.166, 0.134, -0.08, -0.014], "equity": [null, 0.241, -0.288, 0.267, 0.205, -0.11, -0.005], "liabilities_and_equity": [null, 0.211, -0.102, 0.685, 0.638, 0.195, -0.059]}, "cashflow_yoy": {"fiscal_year": ["2014", "2015", "2016", "2017", "2018", "2019", "2020"], "net_income": [null, 0.267, -0.34, 0.071, -0.083, -1.416, -0.72], "depreciation_and_amortization": [null, 1.321, 0.204, -0.05, 0.072, 0.122, -0.149], "non_cash_items": [null, -2.2, 2.771, -0.431, -0.107, 6.641, -0.72], "change_in_working_capital": [null, -3.662, -0.558, 0.962, -2.038, -1.81, 1.106], "cash_fr_operating": [null, 0.976, -0.174, 0.028, -0.346, 0.238, -0.274], "change_in_ppe_and_intangibles": [null, 0.783, -0.553, -0.278, 0.484, 0.232, -0.502], "net_cash_fr_acq_disp": [null, null, null, 1.946, 0.325, -0.993, 0.0], "cash_fr_investing": [null, 0.771, 0.712, 1.359, 0.387, -1.029, -3.0], "cash_fr_debt_issued": [null, null, -21.857, 4.048, 1.233, -1.239, 1.203], "cash_fr_equity_issued": [null, -72.25, -0.127, -0.651, -0.49, -0.424, -1.02], "cash_fr_financing": [null, -17.667, -0.263, -1.461, 2.714, -1.342, 0.751], "net_change_in_cash": [null, -1.571, 0.707, -0.86, -1.136, 45.667, -1.852]}, "ratios": {"fiscal_year": ["2014", "2015", "2016", "2017", "2018", "2019", "2020"], "gp_margin": [0.609, 0.594, 0.592, 0.606, 0.607, 0.589, 0.64], "ebit_margin": [0.305, 0.251, 0.2, 0.191, 0.168, 0.101, 0.09], "ni_margin": [0.199, 0.177, 0.123, 0.125, 0.103, -0.04, -0.015], "roe": [null, 0.463, 0.246, 0.37, 0.268, -0.091, -0.028], "roa": [null, 0.377, 0.206, 0.245, 0.133, -0.033, -0.008], "debt_to_equity": [0.0, 0.0, 0.083, 0.432, 1.053, 1.005, 0.622], "net_debt_to_equity": [-0.538, -0.436, -0.059, 0.352, 0.983, 0.732, 0.515], "cash_to_equity": [0.538, 0.436, 0.142, 0.081, 0.071, 0.273, 0.108], "cash_to_assets": [0.438, 0.364, 0.094, 0.04, 0.026, 0.075, 0.031], "ppe_to_assets": [0.158, 0.209, 0.245, 0.144, 0.092, 0.071, 0.065], "payout_ratio": [0.0, 0.0, 0.0, 0.0, 0.0, -0.0, -0.0]}}