{"income": {"fiscal_year": ["2017", "2018", "2019", "2020"], "quarter_count": [4, 4, 4, 4], "latest_quarter": ["Q4", "Q4", "Q4", "Q4"], "revenue": [119, 127, 170, 162], "cost_of_revenue": [-93, -97, -150, -154], "gross_profit": [25, 29, 17, 7], "operating_expenses": [-12, -18, -23, -23], "selling_general_and_admin": [-12, -14, -19, -19], "operating_income": [12, 11, -5, -18], "non_operating_income": [0, 0, 1, -1], "interest_expense_net": [0, 0, 0, -1], "pretax_income_adj": [10, 11, -6, -19], "abnormal_gains": [0, 2, -1, -6], "pretax_income": [10, 14, -7, -26], "income_tax_net": [-5, 6, 0, 8], "income_fr_continuing_ops": [6, 19, -5, -17], "net_income": [6, 19, -5, -15]}, "balance": {"fiscal_year": ["2017", "2018", "2019", "2020"], "latest_quarter": ["Q4", "Q4", "Q4", "Q4"], "shares_basic": [14, 17, 17, 17], "shares_diluted": [13, 18, 17, 17], "receivables": [10, 14, 18, 16], "current_assets": [23, 31, 35, 42], "ppe_net": [188, 225, 248, 242], "lt_inv_and_receivables": [36, 42, 75, 61], "other_lt_assets": [91, 121, 41, 43], "non_current_assets": [315, 390, 364, 347], "assets": [339, 421, 399, 389], "payables": [20, 23, 28, 28], "st_debt": [3, 3, 3, 3], "current_liabilities": [23, 27, 31, 31], "lt_debt": [102, 76, 105, 122], "non_current_liabilities": [167, 164, 135, 151], "liabilities": [191, 191, 167, 183], "share_capital": [94, 159, 160, 162], "treasury_stock": [0, 0, 0, -3], "retained_earnings": [34, 50, 53, 30], "equity": [147, 229, 232, 206], "liabilities_and_equity": [339, 421, 399, 389]}, "cashflow": {"fiscal_year": ["2017", "2018", "2019", "2020"], "quarter_count": [4, 4, 4, 4], "latest_quarter": ["Q4", "Q4", "Q4", "Q4"], "net_income": [6, 19, -5, -17], "depreciation_and_amortization": [4, 5, 8, 8], "non_cash_items": [2, -8, 0, 8], "change_in_working_capital": [0, -2, 0, -9], "cash_fr_operating": [18, 19, 2, -11], "change_in_ppe_and_intangibles": [-11, -11, -9, -3], "net_cash_fr_acq_disp": [-12, -37, -10, 9], "cash_fr_investing": [-25, -49, -22, 4], "dividends_paid": [0, -4, -4, -4], "cash_fr_debt_issued": [12, -26, 28, 17], "cash_fr_equity_issued": [0, 64, 0, -2], "cash_fr_financing": [8, 31, 22, 9]}, "income_yoy": {"fiscal_year": ["2017", "2018", "2019", "2020"], "revenue": [null, 0.067, 0.339, -0.047], "cost_of_revenue": [null, 0.043, 0.546, 0.027], "gross_profit": [null, 0.16, -0.414, -0.588], "operating_expenses": [null, 0.5, 0.278, 0.0], "selling_general_and_admin": [null, 0.167, 0.357, 0.0], "operating_income": [null, -0.083, -1.455, 2.6], "non_operating_income": [null, null, null, -2.0], "interest_expense_net": [null, null, null, null], "pretax_income_adj": [null, 0.1, -1.545, 2.167], "abnormal_gains": [null, null, -1.5, 5.0], "pretax_income": [null, 0.4, -1.5, 2.714], "income_tax_net": [null, -2.2, -1.0, null], "income_fr_continuing_ops": [null, 2.167, -1.263, 2.4], "net_income": [null, 2.167, -1.263, 2.0]}, "balance_yoy": {"fiscal_year": ["2017", "2018", "2019", "2020"], "receivables": [null, 0.4, 0.286, -0.111], "current_assets": [null, 0.348, 0.129, 0.2], "ppe_net": [null, 0.197, 0.102, -0.024], "lt_inv_and_receivables": [null, 0.167, 0.786, -0.187], "other_lt_assets": [null, 0.33, -0.661, 0.049], "non_current_assets": [null, 0.238, -0.067, -0.047], "assets": [null, 0.242, -0.052, -0.025], "payables": [null, 0.15, 0.217, 0.0], "st_debt": [null, 0.0, 0.0, 0.0], "current_liabilities": [null, 0.174, 0.148, 0.0], "lt_debt": [null, -0.255, 0.382, 0.162], "non_current_liabilities": [null, -0.018, -0.177, 0.119], "liabilities": [null, 0.0, -0.126, 0.096], "share_capital": [null, 0.691, 0.006, 0.012], "treasury_stock": [null, null, null, null], "retained_earnings": [null, 0.471, 0.06, -0.434], "equity": [null, 0.558, 0.013, -0.112], "liabilities_and_equity": [null, 0.242, -0.052, -0.025]}, "cashflow_yoy": {"fiscal_year": ["2017", "2018", "2019", "2020"], "net_income": [null, 2.167, -1.263, 2.4], "depreciation_and_amortization": [null, 0.25, 0.6, 0.0], "non_cash_items": [null, -5.0, -1.0, null], "change_in_working_capital": [null, null, -1.0, null], "cash_fr_operating": [null, 0.056, -0.895, -6.5], "change_in_ppe_and_intangibles": [null, 0.0, -0.182, -0.667], "net_cash_fr_acq_disp": [null, 2.083, -0.73, -1.9], "cash_fr_investing": [null, 0.96, -0.551, -1.182], "dividends_paid": [null, null, 0.0, 0.0], "cash_fr_debt_issued": [null, -3.167, -2.077, -0.393], "cash_fr_equity_issued": [null, null, -1.0, null], "cash_fr_financing": [null, 2.875, -0.29, -0.591]}, "ratios": {"fiscal_year": ["2017", "2018", "2019", "2020"], "gp_margin": [0.21, 0.228, 0.1, 0.043], "ebit_margin": [0.101, 0.087, -0.029, -0.111], "ni_margin": [0.05, 0.15, -0.029, -0.093], "roe": [null, 0.129, -0.022, -0.065], "roa": [null, 0.056, -0.012, -0.038], "debt_to_equity": [0.714, 0.345, 0.466, 0.607], "net_debt_to_equity": [0.714, 0.345, 0.466, 0.607], "cash_to_equity": [0.0, 0.0, 0.0, 0.0], "cash_to_assets": [0.0, 0.0, 0.0, 0.0], "ppe_to_assets": [0.555, 0.534, 0.622, 0.622], "payout_ratio": [0.0, 0.211, -0.8, -0.267]}}