{"income": {"fiscal_year": ["2015", "2016", "2017", "2018", "2019", "2020"], "quarter_count": [4, 4, 4, 4, 4, 4], "latest_quarter": ["Q4", "Q4", "Q4", "Q4", "Q4", "Q4"], "revenue": [2922, 3379, 3220, 3214, 3160, 2211], "cost_of_revenue": [-1299, -1524, -1562, -1742, -1739, -1543], "gross_profit": [1620, 1853, 1656, 1469, 1420, 668], "operating_expenses": [-1225, -1185, -1124, -1193, -1178, -1173], "selling_general_and_admin": [-1023, -923, -848, -833, -829, -882], "research_and_development": [-201, -260, -275, -360, -348, -289], "operating_income": [394, 666, 529, 275, 239, -505], "non_operating_income": [-244, -382, -430, -330, -234, -246], "interest_expense_net": [-253, -382, -363, -360, -298, -254], "pretax_income_adj": [148, 282, 100, -54, 6, -752], "abnormal_gains": [-40, -49, -37, -3995, -1595, -208], "pretax_income": [107, 231, 63, -4050, -1589, -959], "income_tax_net": [128, 254, 1708, 429, 582, -10], "income_fr_continuing_ops": [235, 487, 1771, -3621, -1006, -969], "net_extraordinary_gains": [86, 153, 363, 14, 10, 24], "net_income": [323, 643, 2132, -3608, -998, -944]}, "balance": {"fiscal_year": ["2015", "2016", "2017", "2018", "2019", "2020"], "latest_quarter": ["Q4", "Q4", "Q4", "Q4", "Q4", "Q4"], "shares_basic": [116, 107, 92, 83, 84, 84], "shares_diluted": [117, 108, 92, 81, 83, 84], "cash_and_st_inv": [365, 342, 1260, 348, 790, 1070], "receivables": [489, 431, 275, 623, 577, 538], "inventories": [262, 350, 128, 322, 312, 344], "current_assets": [1846, 1566, 2285, 1427, 1830, 2304], "ppe_net": [793, 881, 413, 982, 896, 833], "other_lt_assets": [13765, 12758, 12642, 8468, 7611, 6578], "non_current_assets": [14558, 13639, 13055, 9450, 8508, 7411], "assets": [16404, 15206, 15341, 10877, 10338, 9715], "payables": [292, 358, 228, 374, 307, 530], "st_debt": [22, 271, 313, 22, 633, 3587], "current_liabilities": [929, 1307, 1050, 943, 1426, 4118], "lt_debt": [6474, 5880, 6420, 6069, 4741, 0], "non_current_liabilities": [10163, 8914, 7768, 7046, 6971, 4577], "liabilities": [11092, 10222, 8819, 7990, 8398, 8696], "share_capital": [5381, 5447, 5511, 5546, 5581, 5606], "treasury_stock": [-109, -919, -1564, -1617, -1615, -1616], "retained_earnings": [38, 529, 2588, -1017, -2016, -2961], "equity": [5311, 4984, 6522, 2887, 1940, 1019], "liabilities_and_equity": [16404, 15206, 15341, 10877, 10338, 9715]}, "cashflow": {"fiscal_year": ["2015", "2016", "2017", "2018", "2019", "2020"], "quarter_count": [4, 4, 4, 4, 4, 4], "latest_quarter": ["Q4", "Q4", "Q4", "Q4", "Q4", "Q4"], "net_income": [323, 643, 2132, -3608, -998, -944], "depreciation_and_amortization": [671, 833, 807, 850, 949, 884], "non_cash_items": [-133, -408, -2025, 3375, -663, 446], "change_in_working_capital": [33, 116, -188, 44, 1452, 111], "cash_fr_operating": [894, 1183, 726, 664, 740, 497], "change_in_ppe_and_intangibles": [-146, -182, -184, -125, -131, -46], "net_cash_fr_acq_disp": [-2154, 23, 501, -387, 95, -1], "cash_fr_investing": [-2295, -106, 319, -479, -8, -10], "cash_fr_debt_issued": [1161, -468, 550, -1002, -250, -137], "cash_fr_equity_issued": [-57, -637, -645, -56, -1, 0], "cash_fr_financing": [1069, -1160, -129, -1093, -279, -184], "net_change_in_cash": [-343, -85, 917, -911, 453, 302]}, "income_yoy": {"fiscal_year": ["2015", "2016", "2017", "2018", "2019", "2020"], "revenue": [null, 0.156, -0.047, -0.002, -0.017, -0.3], "cost_of_revenue": [null, 0.173, 0.025, 0.115, -0.002, -0.113], "gross_profit": [null, 0.144, -0.106, -0.113, -0.033, -0.53], "operating_expenses": [null, -0.033, -0.051, 0.061, -0.013, -0.004], "selling_general_and_admin": [null, -0.098, -0.081, -0.018, -0.005, 0.064], "research_and_development": [null, 0.294, 0.058, 0.309, -0.033, -0.17], "operating_income": [null, 0.69, -0.206, -0.48, -0.131, -3.113], "non_operating_income": [null, 0.566, 0.126, -0.233, -0.291, 0.051], "interest_expense_net": [null, 0.51, -0.05, -0.008, -0.172, -0.148], "pretax_income_adj": [null, 0.905, -0.645, -1.54, -1.111, -126.333], "abnormal_gains": [null, 0.225, -0.245, 106.973, -0.601, -0.87], "pretax_income": [null, 1.159, -0.727, -65.286, -0.608, -0.396], "income_tax_net": [null, 0.984, 5.724, -0.749, 0.357, -1.017], "income_fr_continuing_ops": [null, 1.072, 2.637, -3.045, -0.722, -0.037], "net_extraordinary_gains": [null, 0.779, 1.373, -0.961, -0.286, 1.4], "net_income": [null, 0.991, 2.316, -2.692, -0.723, -0.054]}, "balance_yoy": {"fiscal_year": ["2015", "2016", "2017", "2018", "2019", "2020"], "cash_and_st_inv": [null, -0.063, 2.684, -0.724, 1.27, 0.354], "receivables": [null, -0.119, -0.362, 1.265, -0.074, -0.068], "inventories": [null, 0.336, -0.634, 1.516, -0.031, 0.103], "current_assets": [null, -0.152, 0.459, -0.375, 0.282, 0.259], "ppe_net": [null, 0.111, -0.531, 1.378, -0.088, -0.07], "other_lt_assets": [null, -0.073, -0.009, -0.33, -0.101, -0.136], "non_current_assets": [null, -0.063, -0.043, -0.276, -0.1, -0.129], "assets": [null, -0.073, 0.009, -0.291, -0.05, -0.06], "payables": [null, 0.226, -0.363, 0.64, -0.179, 0.726], "st_debt": [null, 11.318, 0.155, -0.93, 27.773, 4.667], "current_liabilities": [null, 0.407, -0.197, -0.102, 0.512, 1.888], "lt_debt": [null, -0.092, 0.092, -0.055, -0.219, -1.0], "non_current_liabilities": [null, -0.123, -0.129, -0.093, -0.011, -0.343], "liabilities": [null, -0.078, -0.137, -0.094, 0.051, 0.035], "share_capital": [null, 0.012, 0.012, 0.006, 0.006, 0.004], "treasury_stock": [null, 7.431, 0.702, 0.034, -0.001, 0.001], "retained_earnings": [null, 12.921, 3.892, -1.393, 0.982, 0.469], "equity": [null, -0.062, 0.309, -0.557, -0.328, -0.475], "liabilities_and_equity": [null, -0.073, 0.009, -0.291, -0.05, -0.06]}, "cashflow_yoy": {"fiscal_year": ["2015", "2016", "2017", "2018", "2019", "2020"], "net_income": [null, 0.991, 2.316, -2.692, -0.723, -0.054], "depreciation_and_amortization": [null, 0.241, -0.031, 0.053, 0.116, -0.068], "non_cash_items": [null, 2.068, 3.963, -2.667, -1.196, -1.673], "change_in_working_capital": [null, 2.515, -2.621, -1.234, 32.0, -0.924], "cash_fr_operating": [null, 0.323, -0.386, -0.085, 0.114, -0.328], "change_in_ppe_and_intangibles": [null, 0.247, 0.011, -0.321, 0.048, -0.649], "net_cash_fr_acq_disp": [null, -1.011, 20.783, -1.772, -1.245, -1.011], "cash_fr_investing": [null, -0.954, -4.009, -2.502, -0.983, 0.25], "cash_fr_debt_issued": [null, -1.403, -2.175, -2.822, -0.75, -0.452], "cash_fr_equity_issued": [null, 10.175, 0.013, -0.913, -0.982, -1.0], "cash_fr_financing": [null, -2.085, -0.889, 7.473, -0.745, -0.341], "net_change_in_cash": [null, -0.752, -11.788, -1.993, -1.497, -0.333]}, "ratios": {"fiscal_year": ["2015", "2016", "2017", "2018", "2019", "2020"], "gp_margin": [0.554, 0.548, 0.514, 0.457, 0.449, 0.302], "ebit_margin": [0.135, 0.197, 0.164, 0.086, 0.076, -0.228], "ni_margin": [0.111, 0.19, 0.662, -1.123, -0.316, -0.427], "roe": [null, 0.121, 0.428, -0.553, -0.346, -0.487], "roa": [null, 0.039, 0.14, -0.235, -0.092, -0.091], "debt_to_equity": [1.223, 1.234, 1.032, 2.11, 2.77, 3.52], "net_debt_to_equity": [1.154, 1.166, 0.839, 1.989, 2.363, 2.47], "cash_to_equity": [0.069, 0.069, 0.193, 0.121, 0.407, 1.05], "cash_to_assets": [0.022, 0.022, 0.082, 0.032, 0.076, 0.11], "ppe_to_assets": [0.048, 0.058, 0.027, 0.09, 0.087, 0.086], "payout_ratio": [0.0, 0.0, 0.0, -0.0, -0.0, -0.0]}}