{"income": {"fiscal_year": ["2012", "2013", "2014", "2015", "2016", "2017", "2018"], "quarter_count": [4, 4, 4, 4, 4, 4, 4], "latest_quarter": ["Q4", "Q4", "Q4", "Q4", "Q4", "Q4", "Q4"], "revenue": [915, 992, 963, 879, 838, 890, 909], "net_revenue_ex_prov": [915, 992, 963, 879, 838, 890, 909], "non_interest_expense": [-916, -949, -945, -881, -858, -869, -865], "operating_income": [-1, 42, 16, -2, -20, 19, 43], "pretax_income": [-1, 42, 16, -2, -20, 19, 43], "income_tax_net": [-1, -15, -10, 0, 11, 1, -14], "income_fr_continuing_ops": [0, 24, 5, -2, -8, 22, 27], "net_extraordinary_gains": [0, 0, 0, 2, 9, 0, 0], "net_income": [-3, 23, 8, 2, 1, 23, 27]}, "balance": {"fiscal_year": ["2012", "2013", "2014", "2015", "2016", "2017", "2018"], "latest_quarter": ["Q4", "Q4", "Q4", "Q4", "Q4", "Q4", "Q4"], "shares_basic": [13, 13, 13, 13, 13, 13, 13], "shares_diluted": [12, 14, 14, 12, 13, 14, 14], "cash_and_st_inv": [135, 98, 63, 63, 64, 48, 90], "receivables": [527, 412, 353, 410, 250, 230, 211], "interbank_assets": [0, 184, 251, 206, 24, 0, 0], "investments": [841, 992, 917, 784, 745, 968, 905], "net_loans": [817, 868, 864, 840, 847, 848, 720], "ppe_net": [28, 32, 29, 28, 27, 27, 28], "assets": [2678, 2952, 2787, 2698, 2236, 2438, 2240], "st_debt": [889, 1147, 989, 1027, 758, 998, 783], "liabilities": [2173, 2424, 2253, 2172, 1723, 1914, 1694], "share_capital": [101, 102, 107, 101, 101, 95, 95], "retained_earnings": [399, 418, 421, 417, 410, 426, 449], "equity": [505, 527, 533, 525, 513, 523, 545], "liabilities_and_equity": [2678, 2952, 2787, 2698, 2236, 2438, 2240]}, "cashflow": {"fiscal_year": ["2012", "2013", "2014", "2015", "2016", "2017", "2018"], "quarter_count": [4, 4, 4, 4, 4, 4, 4], "latest_quarter": ["Q4", "Q4", "Q4", "Q4", "Q4", "Q4", "Q4"], "net_income": [0, 24, 8, 3, 2, 23, 27], "depreciation_and_amortization": [16, 9, 8, 7, 6, 4, 4], "non_cash_items": [-11, 50, 25, 18, 13, 22, 18], "change_in_working_capital": [-16, -92, 30, -51, -73, -67, 110], "cash_fr_operating": [-8, -3, 78, -21, -67, -16, 165], "change_in_ppe_and_intangibles": [-13, -12, -3, -4, -3, -4, -7], "cash_fr_investing": [-13, -12, -3, -4, 40, -3, -7], "dividends_paid": [-4, -4, -4, -4, -10, -7, -4], "cash_fr_equity_issued": [-1, -3, 0, -7, -3, -6, -5], "cash_fr_financing": [88, -20, -108, 27, 28, 3, -115], "net_change_in_cash": [64, -36, -35, 0, 3, -16, 44]}}