{"income": {"fiscal_year": ["2018", "2019", "2020"], "quarter_count": [4, 4, 4], "latest_quarter": ["Q4", "Q4", "Q4"], "revenue": [6, 12, 75], "operating_expenses": [-61, -102, -200], "selling_general_and_admin": [-11, -22, -41], "research_and_development": [-47, -76, -157], "operating_income": [-53, -87, -124], "non_operating_income": [3, 2, 0], "pretax_income_adj": [-48, -83, -123], "abnormal_gains": [1, 0, 0], "pretax_income": [-47, -83, -122], "income_fr_continuing_ops": [-47, -83, -122], "net_income": [-47, -83, -122]}, "balance": {"fiscal_year": ["2018", "2019", "2020"], "latest_quarter": ["Q4", "Q4", "Q4"], "shares_basic": [43, 44, 63], "shares_diluted": [43, 44, 63], "cash_and_st_inv": [256, 188, 728], "current_assets": [258, 192, 735], "ppe_net": [11, 9, 10], "lt_inv_and_receivables": [4, 0, 6], "other_lt_assets": [0, 1, 19], "non_current_assets": [15, 10, 36], "assets": [274, 203, 772], "payables": [9, 14, 43], "current_liabilities": [16, 22, 121], "non_current_liabilities": [23, 16, 148], "liabilities": [39, 39, 269], "share_capital": [357, 369, 830], "retained_earnings": [-122, -205, -328], "equity": [234, 163, 502], "liabilities_and_equity": [274, 203, 772]}, "cashflow": {"fiscal_year": ["2018", "2019", "2020"], "quarter_count": [4, 4, 4], "latest_quarter": ["Q4", "Q4", "Q4"], "net_income": [-47, -83, -122], "non_cash_items": [1, 7, 20], "change_in_working_capital": [1, 1, 209], "cash_fr_operating": [-41, -71, 113], "change_in_ppe_and_intangibles": [-305, 0, -2], "change_in_lt_investment": [16, -249, -737], "cash_fr_investing": [-113, 58, -434], "cash_fr_equity_issued": [2, 0, 436], "cash_fr_financing": [128, 0, 436], "net_change_in_cash": [-27, -14, 115]}}