{"income": {"fiscal_year": ["2017", "2018", "2019", "2020"], "quarter_count": [4, 4, 4, 4], "latest_quarter": ["Q4", "Q4", "Q4", "Q4"], "revenue": [2439, 2503, 2645, 2847], "cost_of_revenue": [-1589, -1519, -1550, -1521], "gross_profit": [847, 984, 1093, 1324], "operating_expenses": [-716, -722, -730, -857], "selling_general_and_admin": [-716, -722, -730, -857], "operating_income": [130, 260, 360, 465], "non_operating_income": [-61, -66, -85, -67], "interest_expense_net": [-61, -66, -85, -67], "pretax_income_adj": [69, 192, 273, 396], "abnormal_gains": [-37, -32, -6, -20], "pretax_income": [30, 159, 267, 377], "income_tax_net": [-28, -23, -46, -103], "income_fr_continuing_ops": [3, 134, 218, 271], "net_income": [3, 134, 218, 271]}, "balance": {"fiscal_year": ["2017", "2018", "2019", "2020"], "latest_quarter": ["Q4", "Q4", "Q4", "Q4"], "shares_basic": [20, 20, 19, 19], "shares_diluted": [25, 25, 25, 26], "cash_and_st_inv": [17, 5, 47, 100], "receivables": [31, 40, 48, 59], "inventories": [527, 531, 438, 544], "current_assets": [644, 703, 596, 801], "ppe_net": [800, 952, 967, 1077], "lt_inv_and_receivables": [0, 0, 0, 100], "other_lt_assets": [287, 766, 881, 919], "non_current_assets": [1087, 1719, 1848, 2096], "assets": [1732, 2423, 2445, 2898], "payables": [318, 320, 330, 424], "st_debt": [0, 343, 290, 2], "current_liabilities": [519, 992, 982, 921], "lt_debt": [1089, 999, 1005, 1064], "non_current_liabilities": [1220, 1469, 1444, 1529], "liabilities": [1740, 2461, 2427, 2451], "share_capital": [840, 356, 430, 581], "treasury_stock": [-1000, 0, 0, 0], "retained_earnings": [152, -392, -409, -137], "equity": [-7, -38, 18, 447], "liabilities_and_equity": [1732, 2423, 2445, 2898]}, "cashflow": {"fiscal_year": ["2017", "2018", "2019", "2020"], "quarter_count": [4, 4, 4, 4], "latest_quarter": ["Q4", "Q4", "Q4", "Q4"], "net_income": [-1, 134, 218, 271], "depreciation_and_amortization": [82, 89, 99, 98], "non_cash_items": [233, 202, 98, 235], "change_in_working_capital": [159, -181, -80, -106], "cash_fr_operating": [472, 248, 337, 500], "change_in_ppe_and_intangibles": [-53, -78, -68, -84], "change_in_lt_investment": [175, 0, 0, 0], "net_cash_fr_acq_disp": [0, 0, 0, -18], "cash_fr_investing": [122, -78, -121, -195], "cash_fr_debt_issued": [294, 124, 152, -250], "cash_fr_equity_issued": [-975, -206, -224, 12], "cash_fr_financing": [-684, -188, -173, -243], "net_change_in_cash": [-88, -18, 41, 59]}, "income_yoy": {"fiscal_year": ["2017", "2018", "2019", "2020"], "revenue": [null, 0.026, 0.057, 0.076], "cost_of_revenue": [null, -0.044, 0.02, -0.019], "gross_profit": [null, 0.162, 0.111, 0.211], "operating_expenses": [null, 0.008, 0.011, 0.174], "selling_general_and_admin": [null, 0.008, 0.011, 0.174], "operating_income": [null, 1.0, 0.385, 0.292], "non_operating_income": [null, 0.082, 0.288, -0.212], "interest_expense_net": [null, 0.082, 0.288, -0.212], "pretax_income_adj": [null, 1.783, 0.422, 0.451], "abnormal_gains": [null, -0.135, -0.812, 2.333], "pretax_income": [null, 4.3, 0.679, 0.412], "income_tax_net": [null, -0.179, 1.0, 1.239], "income_fr_continuing_ops": [null, 43.667, 0.627, 0.243], "net_income": [null, 43.667, 0.627, 0.243]}, "balance_yoy": {"fiscal_year": ["2017", "2018", "2019", "2020"], "cash_and_st_inv": [null, -0.706, 8.4, 1.128], "receivables": [null, 0.29, 0.2, 0.229], "inventories": [null, 0.008, -0.175, 0.242], "current_assets": [null, 0.092, -0.152, 0.344], "ppe_net": [null, 0.19, 0.016, 0.114], "lt_inv_and_receivables": [null, null, null, null], "other_lt_assets": [null, 1.669, 0.15, 0.043], "non_current_assets": [null, 0.581, 0.075, 0.134], "assets": [null, 0.399, 0.009, 0.185], "payables": [null, 0.006, 0.031, 0.285], "st_debt": [null, null, -0.155, -0.993], "current_liabilities": [null, 0.911, -0.01, -0.062], "lt_debt": [null, -0.083, 0.006, 0.059], "non_current_liabilities": [null, 0.204, -0.017, 0.059], "liabilities": [null, 0.414, -0.014, 0.01], "share_capital": [null, -0.576, 0.208, 0.351], "treasury_stock": [null, -1.0, null, null], "retained_earnings": [null, -3.579, 0.043, -0.665], "equity": [null, 4.429, -1.474, 23.833], "liabilities_and_equity": [null, 0.399, 0.009, 0.185]}, "cashflow_yoy": {"fiscal_year": ["2017", "2018", "2019", "2020"], "net_income": [null, -135.0, 0.627, 0.243], "depreciation_and_amortization": [null, 0.085, 0.112, -0.01], "non_cash_items": [null, -0.133, -0.515, 1.398], "change_in_working_capital": [null, -2.138, -0.558, 0.325], "cash_fr_operating": [null, -0.475, 0.359, 0.484], "change_in_ppe_and_intangibles": [null, 0.472, -0.128, 0.235], "change_in_lt_investment": [null, -1.0, null, null], "net_cash_fr_acq_disp": [null, null, null, null], "cash_fr_investing": [null, -1.639, 0.551, 0.612], "cash_fr_debt_issued": [null, -0.578, 0.226, -2.645], "cash_fr_equity_issued": [null, -0.789, 0.087, -1.054], "cash_fr_financing": [null, -0.725, -0.08, 0.405], "net_change_in_cash": [null, -0.795, -3.278, 0.439]}, "ratios": {"fiscal_year": ["2017", "2018", "2019", "2020"], "gp_margin": [0.347, 0.393, 0.413, 0.465], "ebit_margin": [0.053, 0.104, 0.136, 0.163], "ni_margin": [0.001, 0.054, 0.082, 0.095], "roe": [null, -19.143, -5.737, 15.056], "roa": [null, 0.077, 0.09, 0.111], "debt_to_equity": [-155.571, -35.316, 71.944, 2.385], "net_debt_to_equity": [-153.143, -35.184, 69.333, 2.161], "cash_to_equity": [-2.429, -0.132, 2.611, 0.224], "cash_to_assets": [0.01, 0.002, 0.019, 0.035], "ppe_to_assets": [0.462, 0.393, 0.396, 0.372], "payout_ratio": [0.0, 0.0, 0.0, 0.0]}}