{"income": {"fiscal_year": ["2017", "2018", "2019", "2020"], "quarter_count": [4, 4, 4, 4], "latest_quarter": ["Q4", "Q4", "Q4", "Q4"], "revenue": [6652, 7095, 7284, 7983], "cost_of_revenue": [-3250, -3407, -3605, -3927], "gross_profit": [3400, 3685, 3678, 4053], "operating_expenses": [-791, -805, -925, -932], "selling_general_and_admin": [-92, -101, -130, -125], "research_and_development": [-27, -29, -29, -30], "depreciation_and_amortization": [-670, -673, -762, -773], "operating_income": [2608, 2879, 2750, 3119], "non_operating_income": [-315, -290, -325, -373], "interest_expense_net": [-349, -343, -349, -372], "pretax_income_adj": [2291, 2588, 2424, 2743], "abnormal_gains": [10, 0, 0, 0], "pretax_income": [2301, 2588, 2424, 2743], "income_tax_net": [-1592, -1051, -944, -1172], "income_fr_continuing_ops": [731, 1546, 1491, 1576], "net_income": [727, 1541, 1484, 1569]}, "balance": {"fiscal_year": ["2017", "2018", "2019", "2020"], "latest_quarter": ["Q4", "Q4", "Q4", "Q4"], "shares_basic": [773, 773, 773, 773], "shares_diluted": [773, 773, 773, 773], "cash_and_st_inv": [1055, 1058, 2005, 2594], "receivables": [890, 972, 911, 1068], "inventories": [1041, 1032, 1068, 950], "current_assets": [3170, 3180, 4184, 4815], "ppe_net": [9099, 9403, 9371, 9458], "lt_inv_and_receivables": [99, 103, 111, 114], "other_lt_assets": [1410, 1600, 2739, 2558], "non_current_assets": [10610, 11107, 12222, 12131], "assets": [13780, 14287, 16407, 16946], "payables": [1168, 1216, 1008, 1314], "st_debt": [0, 0, 399, 0], "current_liabilities": [1168, 1216, 1476, 1384], "lt_debt": [5957, 5960, 6541, 6544], "non_current_liabilities": [6462, 6458, 8072, 8285], "liabilities": [7630, 7674, 9549, 9670], "share_capital": [3382, 3402, 3433, 3450], "treasury_stock": [-3001, -3019, -3048, -3063], "retained_earnings": [5726, 6186, 6435, 6846], "equity": [6149, 6612, 6858, 7276], "liabilities_and_equity": [13780, 14287, 16407, 16946]}, "cashflow": {"fiscal_year": ["2017", "2018", "2019", "2020"], "quarter_count": [4, 4, 4, 4], "latest_quarter": ["Q4", "Q4", "Q4", "Q4"], "net_income": [731, 1546, 1491, 1576], "depreciation_and_amortization": [670, 673, 762, 773], "non_cash_items": [664, -12, 2, -52], "change_in_working_capital": [-90, 23, -348, 483], "cash_fr_operating": [1975, 2233, 1911, 2782], "change_in_ppe_and_intangibles": [-1022, -1120, -706, -591], "change_in_lt_investment": [1, -164, 416, 120], "cash_fr_investing": [-1017, -1294, -572, -914], "dividends_paid": [-454, -1080, -1236, -1158], "cash_fr_debt_issued": [0, 0, 987, -400], "cash_fr_financing": [-454, -1081, -261, -1561], "net_change_in_cash": [457, -159, 1081, 258]}}