{"income": {"fiscal_year": ["2020"], "quarter_count": [4], "latest_quarter": ["Q4"], "revenue": [1292], "provision_loan_losses": [-205], "net_revenue_ex_prov": [1087], "non_interest_expense": [-760], "operating_income": [327], "pretax_income": [-1458], "income_tax_net": [-66], "income_fr_continuing_ops": [-1525], "net_income": [-1525]}, "balance": {"fiscal_year": ["2020"], "latest_quarter": ["Q4"], "shares_basic": [220], "shares_diluted": [220], "cash_and_st_inv": [2573], "investments": [3342], "net_loans": [21450], "ppe_net": [178], "assets": [29235], "st_debt": [375], "lt_debt": [1114], "liabilities": [26530], "share_capital": [3514], "retained_earnings": [-932], "equity": [2704], "liabilities_and_equity": [29235]}, "cashflow": {"fiscal_year": ["2020"], "quarter_count": [4], "latest_quarter": ["Q4"], "net_income": [-1525], "depreciation_and_amortization": [35], "non_cash_items": [8240], "provision_for_losses": [205], "change_in_working_capital": [-6865], "cash_fr_operating": [94], "change_in_ppe_and_intangibles": [-10], "change_in_loans": [-751], "cash_fr_investing": [-961], "dividends_paid": [-184], "cash_fr_debt_issued": [-135], "cash_fr_equity_issued": [-8], "cash_fr_financing": [2077], "net_change_in_cash": [1209]}, "income_yoy": {"fiscal_year": ["2020"], "revenue": [null], "provision_loan_losses": [null], "net_revenue_ex_prov": [null], "non_interest_expense": [null], "operating_income": [null], "pretax_income": [null], "income_tax_net": [null], "income_fr_continuing_ops": [null], "net_income": [null]}, "balance_yoy": {"fiscal_year": ["2020"], "cash_and_st_inv": [null], "investments": [null], "net_loans": [null], "ppe_net": [null], "assets": [null], "st_debt": [null], "lt_debt": [null], "liabilities": [null], "share_capital": [null], "retained_earnings": [null], "equity": [null], "liabilities_and_equity": [null]}, "cashflow_yoy": {"fiscal_year": ["2020"], "net_income": [null], "depreciation_and_amortization": [null], "non_cash_items": [null], "provision_for_losses": [null], "change_in_working_capital": [null], "cash_fr_operating": [null], "change_in_ppe_and_intangibles": [null], "change_in_loans": [null], "cash_fr_investing": [null], "dividends_paid": [null], "cash_fr_debt_issued": [null], "cash_fr_equity_issued": [null], "cash_fr_financing": [null], "net_change_in_cash": [null]}, "ratios": {"fiscal_year": ["2020"], "gp_margin": [null], "ebit_margin": [0.253], "ni_margin": [-1.18], "roe": [null], "roa": [null], "debt_to_equity": [0.551], "net_debt_to_equity": [-0.401], "cash_to_equity": [0.952], "cash_to_assets": [0.088], "ppe_to_assets": [0.006], "payout_ratio": [-0.121]}}