{"income": {"fiscal_year": ["2017", "2018", "2019", "2020"], "quarter_count": [4, 4, 4, 4], "latest_quarter": ["Q4", "Q4", "Q4", "Q4"], "revenue": [7677, 8174, 8358, 12323], "cost_of_revenue": [-6192, -6608, -6775, -9996], "gross_profit": [1484, 1565, 1579, 2325], "operating_expenses": [-1162, -1212, -1233, -1979], "selling_general_and_admin": [-1098, -1150, -1170, -1856], "depreciation_and_amortization": [-62, -60, -61, -120], "operating_income": [318, 351, 343, 345], "non_operating_income": [-66, -69, -63, -222], "interest_expense_net": [-68, -68, -65, -225], "pretax_income_adj": [250, 279, 280, 122], "pretax_income": [250, 279, 280, 122], "income_tax_net": [-87, -53, -57, -24], "income_fr_continuing_ops": [161, 223, 220, 100], "net_income": [161, 225, 222, 99]}, "balance": {"fiscal_year": ["2017", "2018", "2019", "2020"], "latest_quarter": ["Q4", "Q4", "Q4", "Q4"], "shares_basic": [46, 45, 41, 50], "shares_diluted": [47, 46, 42, 51], "cash_and_st_inv": [117, 96, 150, 449], "receivables": [1170, 1166, 1187, 2466], "inventories": [956, 948, 1011, 2163], "current_assets": [2408, 2385, 2540, 5506], "ppe_net": [156, 160, 181, 399], "other_lt_assets": [2170, 2058, 2295, 5974], "non_current_assets": [2326, 2219, 2477, 6373], "assets": [4735, 4605, 5017, 11880], "payables": [872, 882, 879, 1905], "st_debt": [72, 74, 26, 528], "current_liabilities": [1040, 1061, 1084, 2986], "lt_debt": [1313, 1167, 1257, 4369], "non_current_liabilities": [1578, 1413, 1674, 5556], "liabilities": [2619, 2475, 2758, 8543], "share_capital": [999, 994, 1039, 1943], "treasury_stock": [-647, -758, -937, -938], "retained_earnings": [2079, 2307, 2530, 2601], "equity": [2116, 2129, 2258, 3336], "liabilities_and_equity": [4735, 4605, 5017, 11880]}, "cashflow": {"fiscal_year": ["2017", "2018", "2019", "2020"], "quarter_count": [4, 4, 4, 4], "latest_quarter": ["Q4", "Q4", "Q4", "Q4"], "net_income": [161, 223, 220, 100], "depreciation_and_amortization": [62, 60, 61, 120], "non_cash_items": [-37, 20, 19, -9], "change_in_working_capital": [-41, -13, -82, 330], "cash_fr_operating": [148, 294, 223, 542], "change_in_ppe_and_intangibles": [-14, -22, -41, -37], "net_cash_fr_acq_disp": [0, 0, -27, -3708], "cash_fr_investing": [-4, -34, -59, -3734], "dividends_paid": [0, 0, 0, -29], "cash_fr_debt_issued": [-31, -125, 58, 3590], "cash_fr_equity_issued": [-106, -126, -150, 0], "cash_fr_financing": [-139, -273, -110, 3481], "net_change_in_cash": [7, -22, 53, 297]}, "income_yoy": {"fiscal_year": ["2017", "2018", "2019", "2020"], "revenue": [null, 0.065, 0.023, 0.474], "cost_of_revenue": [null, 0.067, 0.025, 0.475], "gross_profit": [null, 0.055, 0.009, 0.472], "operating_expenses": [null, 0.043, 0.017, 0.605], "selling_general_and_admin": [null, 0.047, 0.017, 0.586], "depreciation_and_amortization": [null, -0.032, 0.017, 0.967], "operating_income": [null, 0.104, -0.023, 0.006], "non_operating_income": [null, 0.045, -0.087, 2.524], "interest_expense_net": [null, 0.0, -0.044, 2.462], "pretax_income_adj": [null, 0.116, 0.004, -0.564], "pretax_income": [null, 0.116, 0.004, -0.564], "income_tax_net": [null, -0.391, 0.075, -0.579], "income_fr_continuing_ops": [null, 0.385, -0.013, -0.545], "net_income": [null, 0.398, -0.013, -0.554]}, "balance_yoy": {"fiscal_year": ["2017", "2018", "2019", "2020"], "cash_and_st_inv": [null, -0.179, 0.562, 1.993], "receivables": [null, -0.003, 0.018, 1.078], "inventories": [null, -0.008, 0.066, 1.139], "current_assets": [null, -0.01, 0.065, 1.168], "ppe_net": [null, 0.026, 0.131, 1.204], "other_lt_assets": [null, -0.052, 0.115, 1.603], "non_current_assets": [null, -0.046, 0.116, 1.573], "assets": [null, -0.027, 0.089, 1.368], "payables": [null, 0.011, -0.003, 1.167], "st_debt": [null, 0.028, -0.649, 19.308], "current_liabilities": [null, 0.02, 0.022, 1.755], "lt_debt": [null, -0.111, 0.077, 2.476], "non_current_liabilities": [null, -0.105, 0.185, 2.319], "liabilities": [null, -0.055, 0.114, 2.098], "share_capital": [null, -0.005, 0.045, 0.87], "treasury_stock": [null, 0.172, 0.236, 0.001], "retained_earnings": [null, 0.11, 0.097, 0.028], "equity": [null, 0.006, 0.061, 0.477], "liabilities_and_equity": [null, -0.027, 0.089, 1.368]}, "cashflow_yoy": {"fiscal_year": ["2017", "2018", "2019", "2020"], "net_income": [null, 0.385, -0.013, -0.545], "depreciation_and_amortization": [null, -0.032, 0.017, 0.967], "non_cash_items": [null, -1.541, -0.05, -1.474], "change_in_working_capital": [null, -0.683, 5.308, -5.024], "cash_fr_operating": [null, 0.986, -0.241, 1.43], "change_in_ppe_and_intangibles": [null, 0.571, 0.864, -0.098], "net_cash_fr_acq_disp": [null, null, null, 136.333], "cash_fr_investing": [null, 7.5, 0.735, 62.288], "dividends_paid": [null, null, null, null], "cash_fr_debt_issued": [null, 3.032, -1.464, 60.897], "cash_fr_equity_issued": [null, 0.189, 0.19, -1.0], "cash_fr_financing": [null, 0.964, -0.597, -32.645], "net_change_in_cash": [null, -4.143, -3.409, 4.604]}, "ratios": {"fiscal_year": ["2017", "2018", "2019", "2020"], "gp_margin": [0.193, 0.191, 0.189, 0.189], "ebit_margin": [0.041, 0.043, 0.041, 0.028], "ni_margin": [0.021, 0.028, 0.027, 0.008], "roe": [null, 0.106, 0.104, 0.044], "roa": [null, 0.048, 0.048, 0.02], "debt_to_equity": [0.655, 0.583, 0.568, 1.468], "net_debt_to_equity": [0.599, 0.538, 0.502, 1.333], "cash_to_equity": [0.055, 0.045, 0.066, 0.135], "cash_to_assets": [0.025, 0.021, 0.03, 0.038], "ppe_to_assets": [0.033, 0.035, 0.036, 0.034], "payout_ratio": [0.0, 0.0, 0.0, 0.293]}}