{"income": {"fiscal_year": ["2017", "2018", "2019", "2020"], "quarter_count": [4, 4, 4, 4], "latest_quarter": ["Q4", "Q4", "Q4", "Q4"], "revenue": [12, 12, 72, 90], "operating_expenses": [-121, -136, -208, -257], "selling_general_and_admin": [-32, -32, -55, -85], "research_and_development": [-88, -101, -151, -172], "operating_income": [-107, -122, -134, -165], "non_operating_income": [0, 4, 10, 0], "interest_expense_net": [1, 5, 10, 2], "pretax_income_adj": [-106, -116, -123, -164], "pretax_income": [-106, -116, -123, -164], "income_fr_continuing_ops": [-106, -116, -123, -164], "net_income": [-106, -116, -123, -164]}, "balance": {"fiscal_year": ["2017", "2018", "2019", "2020"], "latest_quarter": ["Q4", "Q4", "Q4", "Q4"], "shares_basic": [45, 45, 52, 56], "shares_diluted": [45, 45, 52, 56], "cash_and_st_inv": [277, 291, 431, 849], "current_assets": [285, 306, 449, 893], "ppe_net": [6, 7, 6, 7], "lt_inv_and_receivables": [95, 0, 22, 7], "other_lt_assets": [1, 1, 25, 23], "non_current_assets": [103, 8, 54, 39], "assets": [389, 314, 504, 932], "payables": [16, 18, 27, 53], "current_liabilities": [16, 18, 33, 60], "non_current_liabilities": [7, 3, 22, 17], "liabilities": [23, 22, 55, 77], "share_capital": [839, 879, 1160, 1732], "retained_earnings": [-473, -586, -711, -877], "equity": [365, 292, 449, 855], "liabilities_and_equity": [389, 314, 504, 932]}, "cashflow": {"fiscal_year": ["2017", "2018", "2019", "2020"], "quarter_count": [4, 4, 4, 4], "latest_quarter": ["Q4", "Q4", "Q4", "Q4"], "net_income": [-106, -116, -123, -164], "depreciation_and_amortization": [0, 1, 2, 1], "non_cash_items": [27, 22, 27, 35], "change_in_working_capital": [-1, -3, -1, -6], "cash_fr_operating": [-74, -94, -93, -128], "change_in_ppe_and_intangibles": [-2, 0, -1, -1], "change_in_lt_investment": [-61, 124, -68, 29], "cash_fr_investing": [-66, 122, -72, 25], "cash_fr_equity_issued": [214, 16, 257, 535], "cash_fr_financing": [219, 14, 256, 535], "net_change_in_cash": [80, 43, 93, 433]}, "income_yoy": {"fiscal_year": ["2017", "2018", "2019", "2020"], "revenue": [null, 0.0, 5.0, 0.25], "operating_expenses": [null, 0.124, 0.529, 0.236], "selling_general_and_admin": [null, 0.0, 0.719, 0.545], "research_and_development": [null, 0.148, 0.495, 0.139], "operating_income": [null, 0.14, 0.098, 0.231], "non_operating_income": [null, null, 1.5, -1.0], "interest_expense_net": [null, 4.0, 1.0, -0.8], "pretax_income_adj": [null, 0.094, 0.06, 0.333], "pretax_income": [null, 0.094, 0.06, 0.333], "income_fr_continuing_ops": [null, 0.094, 0.06, 0.333], "net_income": [null, 0.094, 0.06, 0.333]}, "balance_yoy": {"fiscal_year": ["2017", "2018", "2019", "2020"], "cash_and_st_inv": [null, 0.051, 0.481, 0.97], "current_assets": [null, 0.074, 0.467, 0.989], "ppe_net": [null, 0.167, -0.143, 0.167], "lt_inv_and_receivables": [null, -1.0, null, -0.682], "other_lt_assets": [null, 0.0, 24.0, -0.08], "non_current_assets": [null, -0.922, 5.75, -0.278], "assets": [null, -0.193, 0.605, 0.849], "payables": [null, 0.125, 0.5, 0.963], "current_liabilities": [null, 0.125, 0.833, 0.818], "non_current_liabilities": [null, -0.571, 6.333, -0.227], "liabilities": [null, -0.043, 1.5, 0.4], "share_capital": [null, 0.048, 0.32, 0.493], "retained_earnings": [null, 0.239, 0.213, 0.233], "equity": [null, -0.2, 0.538, 0.904], "liabilities_and_equity": [null, -0.193, 0.605, 0.849]}, "cashflow_yoy": {"fiscal_year": ["2017", "2018", "2019", "2020"], "net_income": [null, 0.094, 0.06, 0.333], "depreciation_and_amortization": [null, null, 1.0, -0.5], "non_cash_items": [null, -0.185, 0.227, 0.296], "change_in_working_capital": [null, 2.0, -0.667, 5.0], "cash_fr_operating": [null, 0.27, -0.011, 0.376], "change_in_ppe_and_intangibles": [null, -1.0, null, 0.0], "change_in_lt_investment": [null, -3.033, -1.548, -1.426], "cash_fr_investing": [null, -2.848, -1.59, -1.347], "cash_fr_equity_issued": [null, -0.925, 15.062, 1.082], "cash_fr_financing": [null, -0.936, 17.286, 1.09], "net_change_in_cash": [null, -0.462, 1.163, 3.656]}, "ratios": {"fiscal_year": ["2017", "2018", "2019", "2020"], "gp_margin": [0.0, 0.0, 0.0, 0.0], "ebit_margin": [-8.917, -10.167, -1.861, -1.833], "ni_margin": [-8.833, -9.667, -1.708, -1.822], "roe": [null, -0.318, -0.421, -0.365], "roa": [null, -0.298, -0.392, -0.325], "debt_to_equity": [0.0, 0.0, 0.0, 0.0], "net_debt_to_equity": [-0.759, -0.997, -0.96, -0.993], "cash_to_equity": [0.759, 0.997, 0.96, 0.993], "cash_to_assets": [0.712, 0.927, 0.855, 0.911], "ppe_to_assets": [0.015, 0.022, 0.012, 0.008], "payout_ratio": [-0.0, -0.0, -0.0, -0.0]}}